LICENSE.txt
MANIFEST.in
README.rst
iqm.py
setup.py
python_iqm.egg-info/PKG-INFO
python_iqm.egg-info/SOURCES.txt
python_iqm.egg-info/dependency_links.txt
python_iqm.egg-info/top_level.txt