Metadata-Version: 1.0
Name: python-iqm
Version: 0.2.1
Summary: Interquartile Mean pure-Python module
Home-page: https://github.com/ClockworkNet/python-iqm
Author: Timid Robot Zehta
Author-email: tim@clockwork.net
License: MIT License
Download-URL: https://github.com/ClockworkNet/python-iqm/releases
Platform: UNKNOWN
Classifier: Environment :: Console
Classifier: License :: OSI Approved :: MIT License
Classifier: Topic :: Scientific/Engineering :: Mathematics
